dotenvplus/__init__.py
dotenvplus-0.0.10.dist-info/licenses/LICENSE
dotenvplus-0.0.10.dist-info/METADATA
dotenvplus-0.0.10.dist-info/WHEEL
dotenvplus-0.0.10.dist-info/top_level.txt
dotenvplus-0.0.10.dist-info/RECORD
