Metadata-Version: 2.4
Name: dotenvplus
Version: 0.0.10
Summary: Reads key-value pairs from a .env file and supports multiple values with dynamic interpolation.
Author-email: AlexFlipnote <root@alexflipnote.dev>
License-Expression: MIT
Project-URL: Homepage, https://github.com/AlexFlipnote/dotenvplus
Project-URL: Repository, https://github.com/AlexFlipnote/dotenvplus
Keywords: dotenv,env,config,environment,variables,key-value,parser
Requires-Python: >=3.7.0
License-File: LICENSE
Dynamic: license-file
